macsima2mc/CLI.py
macsima2mc/__init__.py
macsima2mc/exceptions.py
macsima2mc/illumination_corr.py
macsima2mc/macsima2mc.py
macsima2mc/mc_tools.py
macsima2mc/ome_schema.py
macsima2mc/ome_writer.py
macsima2mc/qc.py
macsima2mc/templates.py
macsima2mc/tools.py
macsima2mc/version.py
macsima2mc-1.2.6.dist-info/LICENSE
macsima2mc-1.2.6.dist-info/METADATA
macsima2mc-1.2.6.dist-info/WHEEL
macsima2mc-1.2.6.dist-info/entry_points.txt
macsima2mc-1.2.6.dist-info/top_level.txt
macsima2mc-1.2.6.dist-info/RECORD
