Metadata-Version: 2.2
Name: macsima2mc
Version: 1.2.6
Summary: stages MACSima tiles for registration with ASHLAR in MCMICRO.
Author-email: Victor Perez <hhabraxas@gmail.com>, "Miguel A. Ibarra-Arellano" <c180l058j@mozmail.com>
License: BSD-3-Clause
Project-URL: Homepage, https://github.com/SchapiroLabor/macsima2mc
Project-URL: Issues, https://github.com/SchapiroLabor/macsima2mc/issues
Keywords: mcmicro,multiplex imaging,proteomics,macsima,staging
Classifier: Programming Language :: Python :: 3.12
Classifier: Operating System :: OS Independent
Classifier: Intended Audience :: Science/Research
Classifier: License :: OSI Approved :: BSD License
Requires-Python: >=3.12
License-File: LICENSE
Requires-Dist: ome-types==0.5.2
Requires-Dist: numpy
Requires-Dist: tifffile
Requires-Dist: pandas
Requires-Dist: beautifulsoup4
Requires-Dist: scikit-image
Requires-Dist: BaSiCPy
